td_mion_orbitrap/__init__.py
td_mion_orbitrap/blank.py
td_mion_orbitrap/blank_utils.py
td_mion_orbitrap/cli.py
td_mion_orbitrap/integration.py
td_mion_orbitrap/kmd.py
td_mion_orbitrap/main.py
td_mion_orbitrap/norm.py
td_mion_orbitrap/pipeline.py
td_mion_orbitrap/profile_pipeline.py
td_mion_orbitrap/spectrum.py
td_mion_orbitrap/thermo.py
td_mion_orbitrap-0.4.0.dist-info/licenses/LICENSE
td_mion_orbitrap-0.4.0.dist-info/METADATA
td_mion_orbitrap-0.4.0.dist-info/WHEEL
td_mion_orbitrap-0.4.0.dist-info/entry_points.txt
td_mion_orbitrap-0.4.0.dist-info/top_level.txt
td_mion_orbitrap-0.4.0.dist-info/RECORD
