Metadata-Version: 2.4
Name: td_mion_orbitrap
Version: 0.4.0
Summary: CLI pipeline for TD‑MION-Orbitrap thermograms, blanks, KMD
Author: Mihai Ciobanu
Requires-Python: >=3.10
License-File: LICENSE
Requires-Dist: click>=8
Requires-Dist: pymzml>=2.5.11
Requires-Dist: pandas>=2
Requires-Dist: numpy>=1.26
Requires-Dist: matplotlib>=3.9
Requires-Dist: pyyaml>=6
Requires-Dist: pyarrow>=16.0.0
Dynamic: license-file
